Workbook

Sheet Supuestos
A1: CASO INSITE (IESE M-1384) · Revelation Iberia — Supuestos e hipótesis
A2: Las celdas AMARILLAS con texto azul son los inputs del modelo: al cambiarlas se recalculan todos los ratios.
A4: Parámetro | B4: Valor | C4: Unidad | D4: Fuente / justificación
A5: Precio medio de una licencia anual | B5: 200 | C5: miles € | D5: Enunciado: rango 150.000–350.000 €; media en torno a 200.000 €/año.
A6: Precio mínimo de licencia | B6: 150 | C6: miles € | D6: Enunciado: extremo inferior del rango.
A7: Precio máximo de licencia | B7: 350 | C7: miles € | D7: Enunciado: extremo superior del rango.
A8: Coste medio de una demo | B8: 12 | C8: miles € | D8: Enunciado: Revelation estima 12.000 € por demo (datos, interfaz, cuentas y formación).
A9: Permanencia media del cliente | B9: 5 | C9: años | D9: Nota 5 del caso: suponer una permanencia media de 5 años.
A10: Nº de comerciales | B10: 6 | C10: personas | D10: Equipo de ventas de 8 personas = 6 comerciales + 2 de soporte/back-office.
A11: Nº total del equipo de ventas | B11: 8 | C11: personas | D11: Enunciado.
A12: Salario fijo medio del comercial | B12: 55 | C12: miles € | D12: Enunciado: salario fijo anual medio de 55.000 €.
A13: % del coste de la demo asumido por el comercial | B13: 0.05 | C13: % | D13: Nota 4 del caso: en 2021 el comercial soporta el 5% del coste de la demo.
A14: Duración mínima del ciclo de venta | B14: 6 | C14: meses | D14: Enunciado: el proceso de venta dura entre 6 y 9 meses.
A15: Duración máxima del ciclo de venta | B15: 9 | C15: meses | D15: Enunciado: el proceso de venta dura entre 6 y 9 meses.
A17: Nota metodológica
A18: El Anexo 1 no facilita el número de licencias vendidas ni el número de demos entregadas. Ambos se estiman dividiendo la cifra de la cuenta de resultados entre el importe unitario medio: licencias = Ventas netas / Precio medio; demos = Gasto en demos / Coste medio por demo. Son estimaciones razonadas a partir de los datos del caso, no cifras facilitadas por él.

Sheet Cuenta de Resultados
A1: ANEXO 1 — Cuenta de resultados de Revelation para Insite
A2: Solo ventas de nuevas licencias · Cifras en miles de euros
A4: Concepto | B4: 2019 | C4: 2020 | D4: Var. absoluta | E4: Var. % | F4: % s/ventas 2019 | G4: % s/ventas 2020 | H4: Var. (p.p.)
A5: Ventas netas | B5: 12250 | C5: 9632 | D5: =C5-B5 -> -2618 | E5: =IFERROR(C5/B5-1,"n/a") -> -0.21371429 | F5: =IFERROR(B5/B$5,"n/a") -> 1 | G5: =IFERROR(C5/C$5,"n/a") -> 1 | H5: =IFERROR((G5-F5)*100,"n/a") -> 0
A6: Coste de ventas | B6: 3085 | C6: 2503 | D6: =C6-B6 -> -582 | E6: =IFERROR(C6/B6-1,"n/a") -> -0.18865478 | F6: =IFERROR(B6/B$5,"n/a") -> 0.25183673 | G6: =IFERROR(C6/C$5,"n/a") -> 0.25986296 | H6: =IFERROR((G6-F6)*100,"n/a") -> 0.80262221
A7: MARGEN BRUTO | B7: =B5-B6 -> 9165 | C7: =C5-C6 -> 7129 | D7: =C7-B7 -> -2036 | E7: =IFERROR(C7/B7-1,"n/a") -> -0.22214948 | F7: =IFERROR(B7/B$5,"n/a") -> 0.74816327 | G7: =IFERROR(C7/C$5,"n/a") -> 0.74013704 | H7: =IFERROR((G7-F7)*100,"n/a") -> -0.80262221
A8: Gastos de ventas para demos | B8: 998 | C8: 1123 | D8: =C8-B8 -> 125 | E8: =IFERROR(C8/B8-1,"n/a") -> 0.1252505 | F8: =IFERROR(B8/B$5,"n/a") -> 0.081469388 | G8: =IFERROR(C8/C$5,"n/a") -> 0.11659053 | H8: =IFERROR((G8-F8)*100,"n/a") -> 3.5121144
A9: Gastos del equipo de ventas | B9: 1076 | C9: 867 | D9: =C9-B9 -> -209 | E9: =IFERROR(C9/B9-1,"n/a") -> -0.19423792 | F9: =IFERROR(B9/B$5,"n/a") -> 0.087836735 | G9: =IFERROR(C9/C$5,"n/a") -> 0.090012458 | H9: =IFERROR((G9-F9)*100,"n/a") -> 0.21757238
A10: Gastos de marketing | B10: 869 | C10: 903 | D10: =C10-B10 -> 34 | E10: =IFERROR(C10/B10-1,"n/a") -> 0.039125432 | F10: =IFERROR(B10/B$5,"n/a") -> 0.070938776 | G10: =IFERROR(C10/C$5,"n/a") -> 0.09375 | H10: =IFERROR((G10-F10)*100,"n/a") -> 2.2811224
A11: Costes totales de ventas y marketing | B11: =SUM(B8:B10) -> 2943 | C11: =SUM(C8:C10) -> 2893 | D11: =C11-B11 -> -50 | E11: =IFERROR(C11/B11-1,"n/a") -> -0.016989467 | F11: =IFERROR(B11/B$5,"n/a") -> 0.2402449 | G11: =IFERROR(C11/C$5,"n/a") -> 0.30035299 | H11: =IFERROR((G11-F11)*100,"n/a") -> 6.0108092
A12: Desarrollo de productos | B12: 2413 | C12: 1804 | D12: =C12-B12 -> -609 | E12: =IFERROR(C12/B12-1,"n/a") -> -0.25238293 | F12: =IFERROR(B12/B$5,"n/a") -> 0.19697959 | G12: =IFERROR(C12/C$5,"n/a") -> 0.18729236 | H12: =IFERROR((G12-F12)*100,"n/a") -> -0.9687233
A13: Generales y administrativos | B13: 1427 | C13: 1335 | D13: =C13-B13 -> -92 | E13: =IFERROR(C13/B13-1,"n/a") -> -0.064470918 | F13: =IFERROR(B13/B$5,"n/a") -> 0.1164898 | G13: =IFERROR(C13/C$5,"n/a") -> 0.1386005 | H13: =IFERROR((G13-F13)*100,"n/a") -> 2.2110702
A14: MARGEN DE VENTAS | B14: =B7-B11-B12-B13 -> 2382 | C14: =C7-C11-C12-C13 -> 1097 | D14: =C14-B14 -> -1285 | E14: =IFERROR(C14/B14-1,"n/a") -> -0.53946264 | F14: =IFERROR(B14/B$5,"n/a") -> 0.19444898 | G14: =IFERROR(C14/C$5,"n/a") -> 0.1138912 | H14: =IFERROR((G14-F14)*100,"n/a") -> -8.0557784
A15: Gastos generales | B15: 647 | C15: 638 | D15: =C15-B15 -> -9 | E15: =IFERROR(C15/B15-1,"n/a") -> -0.013910355 | F15: =IFERROR(B15/B$5,"n/a") -> 0.052816327 | G15: =IFERROR(C15/C$5,"n/a") -> 0.066237542 | H15: =IFERROR((G15-F15)*100,"n/a") -> 1.3421215
A16: BENEFICIO ANTES DE IMPUESTOS | B16: =B14-B15 -> 1735 | C16: =C14-C15 -> 459 | D16: =C16-B16 -> -1276 | E16: =IFERROR(C16/B16-1,"n/a") -> -0.73544669 | F16: =IFERROR(B16/B$5,"n/a") -> 0.14163265 | G16: =IFERROR(C16/C$5,"n/a") -> 0.047653654 | H16: =IFERROR((G16-F16)*100,"n/a") -> -9.3978999
A18: Nota de conciliación con el Anexo 1 original: (a) el caso recoge un coste total de ventas y marketing de 2.894 en 2020, mientras que la suma de sus tres partidas (1.123 + 867 + 903) da 2.893; (b) el caso recoge un BAI de 458, mientras que 1.097 − 638 da 459. Son diferencias de 1 k€ por redondeo del propio caso, sin efecto en el análisis. El ejercicio 2019 cuadra exactamente. Esta hoja calcula los subtotales con fórmulas, por lo que muestra los importes aritméticamente consistentes.
A21: LECTURA RÁPIDA DE LA CUENTA DE RESULTADOS
A22: • Las ventas netas caen un 21,4% (−2.618 k€) pero el beneficio antes de impuestos se hunde un 73,5% (−1.276 k€): el deterioro es estructural, no solo de volumen.
A23: • El gasto en demos es la ÚNICA partida de coste que crece en términos absolutos (+125 k€, +12,5%) justo en el año en que las ventas se desploman.
A24: • El gasto en demos pasa del 8,1% al 11,7% de las ventas: 3,5 puntos porcentuales de deterioro.
A25: • Los costes totales de ventas y marketing apenas bajan un 1,7% frente a una caída de ventas del 21,4%: la estructura comercial no ha acompañado al negocio.
A26: • El margen bruto se mantiene en el ~74%: el problema no está ni en el producto ni en el precio, está en el proceso comercial.

Sheet Ratios y Análisis
A1: ANÁLISIS DE RATIOS — Revelation Iberia / Insite · 2019 vs 2020
A2: Negro = calculado sobre la cuenta de resultados · Verde = enlaza con la hoja Supuestos
A4: Ratio / Indicador | B4: 2019 | C4: 2020 | D4: Variación | E4: Var. % | F4: Lectura del dato
A5: A. RENTABILIDAD Y ESTRUCTURA DE COSTES
A6: Margen bruto (%) | B6: ='Cuenta de Resultados'!B7/'Cuenta de Resultados'!B5 -> 0.74816327 | C6: ='Cuenta de Resultados'!C7/'Cuenta de Resultados'!C5 -> 0.74013704 | D6: =IFERROR((C6-B6)*100,"n/a") -> -0.80262221 | E6: =IFERROR(C6/B6-1,"n/a") -> -0.010727902 | F6: Estable en ~74%: el problema NO está en el producto ni en el precio.
A7: Margen de ventas (%) | B7: ='Cuenta de Resultados'!B14/'Cuenta de Resultados'!B5 -> 0.19444898 | C7: ='Cuenta de Resultados'!C14/'Cuenta de Resultados'!C5 -> 0.1138912 | D7: =IFERROR((C7-B7)*100,"n/a") -> -8.0557784 | E7: =IFERROR(C7/B7-1,"n/a") -> -0.41428751 | F7: Se desploma: la estructura comercial devora el margen.
A8: Margen neto — BAI (%) | B8: ='Cuenta de Resultados'!B16/'Cuenta de Resultados'!B5 -> 0.14163265 | C8: ='Cuenta de Resultados'!C16/'Cuenta de Resultados'!C5 -> 0.047653654 | D8: =IFERROR((C8-B8)*100,"n/a") -> -9.3978999 | E8: =IFERROR(C8/B8-1,"n/a") -> -0.66354048 | F8: De ~14% a ~5%: se pierden 9 p.p. de rentabilidad en un año.
A9: Coste de ventas s/ ventas (%) | B9: ='Cuenta de Resultados'!B6/'Cuenta de Resultados'!B5 -> 0.25183673 | C9: ='Cuenta de Resultados'!C6/'Cuenta de Resultados'!C5 -> 0.25986296 | D9: =IFERROR((C9-B9)*100,"n/a") -> 0.80262221 | E9: =IFERROR(C9/B9-1,"n/a") -> 0.031870736 | F9: Prácticamente constante (~26%).
A10: Gasto total ventas + marketing s/ ventas (%) | B10: ='Cuenta de Resultados'!B11/'Cuenta de Resultados'!B5 -> 0.2402449 | C10: ='Cuenta de Resultados'!C11/'Cuenta de Resultados'!C5 -> 0.30035299 | D10: =IFERROR((C10-B10)*100,"n/a") -> 6.0108092 | E10: =IFERROR(C10/B10-1,"n/a") -> 0.25019508 | F10: Del 24% al 30%: se gasta más para vender menos.
A11: Gasto en DEMOS s/ ventas (%) | B11: ='Cuenta de Resultados'!B8/'Cuenta de Resultados'!B5 -> 0.081469388 | C11: ='Cuenta de Resultados'!C8/'Cuenta de Resultados'!C5 -> 0.11659053 | D11: =IFERROR((C11-B11)*100,"n/a") -> 3.5121144 | E11: =IFERROR(C11/B11-1,"n/a") -> 0.4310962 | F11: CLAVE DEL CASO: +3,5 p.p. La demo se ha descontrolado.
A12: Gasto en marketing s/ ventas (%) | B12: ='Cuenta de Resultados'!B10/'Cuenta de Resultados'!B5 -> 0.070938776 | C12: ='Cuenta de Resultados'!C10/'Cuenta de Resultados'!C5 -> 0.09375 | D12: =IFERROR((C12-B12)*100,"n/a") -> 2.2811224 | E12: =IFERROR(C12/B12-1,"n/a") -> 0.32156214 | F12: Sube pese a la caída de ventas: 'más marketing, menos ventas'.
A13: Gasto en DEMOS s/ margen bruto (%) | B13: ='Cuenta de Resultados'!B8/'Cuenta de Resultados'!B7 -> 0.10889253 | C13: ='Cuenta de Resultados'!C8/'Cuenta de Resultados'!C7 -> 0.1575256 | D13: =IFERROR((C13-B13)*100,"n/a") -> 4.8633074 | E13: =IFERROR(C13/B13-1,"n/a") -> 0.44661535 | F13: La demo consume una parte creciente del margen generado.
A14: B. VOLUMEN DE ACTIVIDAD (estimado a partir de precios y costes unitarios)
A15: Nº de licencias vendidas (estimado) | B15: ='Cuenta de Resultados'!B5/Supuestos!$B$5 -> 61.25 | C15: ='Cuenta de Resultados'!C5/Supuestos!$B$5 -> 48.16 | D15: =IFERROR(C15-B15,"n/a") -> -13.09 | E15: =IFERROR(C15/B15-1,"n/a") -> -0.21371429 | F15: Ventas netas / precio medio de 200 k€ por licencia.
A16: Nº de demos entregadas (estimado) | B16: ='Cuenta de Resultados'!B8/Supuestos!$B$8 -> 83.166667 | C16: ='Cuenta de Resultados'!C8/Supuestos!$B$8 -> 93.583333 | D16: =IFERROR(C16-B16,"n/a") -> 10.416667 | E16: =IFERROR(C16/B16-1,"n/a") -> 0.1252505 | F16: Gasto en demos / 12 k€ de coste medio por demo.
A17: Demos necesarias por licencia vendida | B17: =IFERROR(B16/B15,"n/a") -> 1.3578231 | C17: =IFERROR(C16/C15,"n/a") -> 1.9431755 | D17: =IFERROR(C17-B17,"n/a") -> 0.5853524 | E17: =IFERROR(C17/B17-1,"n/a") -> 0.4310962 | F17: Se pasa de 1,4 a 1,9 demos por cada venta cerrada.
A18: TASA DE CONVERSIÓN demo → licencia (%) | B18: =IFERROR(B15/B16,"n/a") -> 0.73647295 | C18: =IFERROR(C15/C16,"n/a") -> 0.51462155 | D18: =IFERROR((C18-B18)*100,"n/a") -> -22.18514 | E18: =IFERROR(C18/B18-1,"n/a") -> -0.30123496 | F18: EL DATO CLAVE: del ~74% al ~51%. Se pierden 22 p.p. de eficacia.
A19: C. EFICIENCIA COMERCIAL
A20: Coste de demos por licencia vendida (miles €) | B20: =IFERROR('Cuenta de Resultados'!B8/B15,"n/a") -> 16.293878 | C20: =IFERROR('Cuenta de Resultados'!C8/C15,"n/a") -> 23.318106 | D20: =IFERROR(C20-B20,"n/a") -> 7.0242288 | E20: =IFERROR(C20/B20-1,"n/a") -> 0.4310962 | F20: Cada venta arrastra un 43% más de coste de demo.
A21: Coste de adquisición por licencia — CAC (miles €) | B21: =IFERROR('Cuenta de Resultados'!B11/B15,"n/a") -> 48.04898 | C21: =IFERROR('Cuenta de Resultados'!C11/C15,"n/a") -> 60.070598 | D21: =IFERROR(C21-B21,"n/a") -> 12.021618 | E21: =IFERROR(C21/B21-1,"n/a") -> 0.25019508 | F21: Todo el coste comercial y de marketing repercutido por licencia.
A22: CAC sobre precio de la licencia (%) | B22: =IFERROR(B21/Supuestos!$B$5,"n/a") -> 0.2402449 | C22: =IFERROR(C21/Supuestos!$B$5,"n/a") -> 0.30035299 | D22: =IFERROR((C22-B22)*100,"n/a") -> 6.0108092 | E22: =IFERROR(C22/B22-1,"n/a") -> 0.25019508 | F22: Del 24% al 30% del precio se consume en captar al cliente.
A23: Ventas netas por euro de gasto comercial (x) | B23: =IFERROR('Cuenta de Resultados'!B5/'Cuenta de Resultados'!B11,"n/a") -> 4.1624193 | C23: =IFERROR('Cuenta de Resultados'!C5/'Cuenta de Resultados'!C11,"n/a") -> 3.3294158 | D23: =IFERROR(C23-B23,"n/a") -> -0.83300347 | E23: =IFERROR(C23/B23-1,"n/a") -> -0.20012483 | F23: Retorno del gasto comercial: cae de 4,16x a 3,33x.
A24: Ventas netas por comercial (miles €) | B24: =IFERROR('Cuenta de Resultados'!B5/Supuestos!$B$10,"n/a") -> 2041.6667 | C24: =IFERROR('Cuenta de Resultados'!C5/Supuestos!$B$10,"n/a") -> 1605.3333 | D24: =IFERROR(C24-B24,"n/a") -> -436.33333 | E24: =IFERROR(C24/B24-1,"n/a") -> -0.21371429 | F24: Productividad individual: −21,4% con el mismo equipo.
A25: Licencias vendidas por comercial | B25: =IFERROR(B15/Supuestos!$B$10,"n/a") -> 10.208333 | C25: =IFERROR(C15/Supuestos!$B$10,"n/a") -> 8.0266667 | D25: =IFERROR(C25-B25,"n/a") -> -2.1816667 | E25: =IFERROR(C25/B25-1,"n/a") -> -0.21371429 | F25: De ~10 a ~8 licencias por comercial y año.
A26: Demos gestionadas por comercial | B26: =IFERROR(B16/Supuestos!$B$10,"n/a") -> 13.861111 | C26: =IFERROR(C16/Supuestos!$B$10,"n/a") -> 15.597222 | D26: =IFERROR(C26-B26,"n/a") -> 1.7361111 | E26: =IFERROR(C26/B26-1,"n/a") -> 0.1252505 | F26: Más esfuerzo de demo por comercial y peor resultado.
A27: D. PUNTO MUERTO DE UNA DEMO (¿cuándo compensa autorizarla?)
A28: Margen bruto de una licencia — año 1 (miles €) | B28: =Supuestos!$B$5*B6 -> 149.63265 | C28: =Supuestos!$B$5*C6 -> 148.02741 | D28: =IFERROR(C28-B28,"n/a") -> -1.6052444 | E28: =IFERROR(C28/B28-1,"n/a") -> -0.010727902 | F28: Precio medio de 200 k€ × margen bruto del ejercicio.
A29: Margen bruto del ciclo de vida — 5 años (miles €) | B29: =B28*Supuestos!$B$9 -> 748.16327 | C29: =C28*Supuestos!$B$9 -> 740.13704 | D29: =IFERROR(C29-B29,"n/a") -> -8.0262221 | E29: =IFERROR(C29/B29-1,"n/a") -> -0.010727902 | F29: Margen anual × permanencia media de 5 años (nota 5 del caso).
A30: Probabilidad mínima de cierre para rentabilizar la demo — 1 año (%) | B30: =IFERROR(Supuestos!$B$8/B28,"n/a") -> 0.080196399 | C30: =IFERROR(Supuestos!$B$8/C28,"n/a") -> 0.081066068 | D30: =IFERROR((C30-B30)*100,"n/a") -> 0.086966883 | E30: =IFERROR(C30/B30-1,"n/a") -> 0.010844238 | F30: Coste de la demo (12 k€) / margen bruto del primer año.
A31: Probabilidad mínima de cierre para rentabilizar la demo — 5 años (%) | B31: =IFERROR(Supuestos!$B$8/B29,"n/a") -> 0.01603928 | C31: =IFERROR(Supuestos!$B$8/C29,"n/a") -> 0.016213214 | D31: =IFERROR((C31-B31)*100,"n/a") -> 0.017393377 | E31: =IFERROR(C31/B31-1,"n/a") -> 0.010844238 | F31: Umbral bajísimo: el coste de la demo NO es el verdadero problema.
A32: Riesgo económico asumido por el comercial en una demo (miles €) | B32: =Supuestos!$B$8*Supuestos!$B$13 -> 0.6 | C32: =Supuestos!$B$8*Supuestos!$B$13 -> 0.6 | D32: =IFERROR(C32-B32,"n/a") -> 0 | E32: =IFERROR(C32/B32-1,"n/a") -> 0 | F32: Solo 600 € (5% de 12.000 €): pedir una demo casi no le cuesta nada.
A33: Riesgo económico asumido por la empresa en una demo (miles €) | B33: =Supuestos!$B$8*(1-Supuestos!$B$13) -> 11.4 | C33: =Supuestos!$B$8*(1-Supuestos!$B$13) -> 11.4 | D33: =IFERROR(C33-B33,"n/a") -> 0 | E33: =IFERROR(C33/B33-1,"n/a") -> 0 | F33: 11.400 € (95%): el incentivo está claramente desalineado.
A35: CONCLUSIONES DEL ANÁLISIS CUANTITATIVO
A36: 1. El margen bruto se mantiene estable en el ~74%: el deterioro de 2020 no procede del producto, del coste de servicio ni del precio, sino del proceso comercial.
A37: 2. Las ventas caen un 21,4% y el beneficio antes de impuestos un 73,5%: el apalancamiento operativo amplifica el problema porque los costes comerciales son casi fijos.
A38: 3. Se entregaron más demos (~94 frente a ~83) y se vendieron menos licencias (~48 frente a ~61): la demo dejó de acompañar a la venta y pasó a sustituirla.
A39: 4. La tasa de conversión demo → licencia cae del ~74% al ~51% (−22 p.p.): es el indicador que resume el problema del caso.
A40: 5. Pero el punto muerto de una demo es solo el 8,1% de probabilidad de cierre a un año (1,6% a cinco años): recortar demos para ahorrar dinero sería un error de diagnóstico.
A41: 6. El recurso escaso no son los 12.000 € de la demo, sino el tiempo de 6 comerciales en ciclos de 6-9 meses. Y quien decide pedirla arriesga 600 € mientras la empresa arriesga 11.400 €.
A42: 7. Conclusión: el problema no es CUÁNTAS demos se dan, sino CUÁNDO se dan y con qué filtro de cualificación previa.
